setup.py
ganb_probability/Binomialdistribution.py
ganb_probability/Gaussiandistribution.py
ganb_probability/Generaldistribution.py
ganb_probability/__init__.py
ganb_probability.egg-info/PKG-INFO
ganb_probability.egg-info/SOURCES.txt
ganb_probability.egg-info/dependency_links.txt
ganb_probability.egg-info/not-zip-safe
ganb_probability.egg-info/top_level.txt