Metadata-Version: 1.0
Name: ganb-probability
Version: 1.0
Summary: Gaussian distributions
Home-page: UNKNOWN
Author: Cecil Wiafe
Author-email: UNKNOWN
License: UNKNOWN
Platform: UNKNOWN
